VeriVerse_day_1/HA/ha.v
module ha (
	input a,
	input b,
	output sum,
	output carry
);

assign sum = a ^ b;  // sum is xor of both inputs
assign carry = a & b;

endmodule

VeriVerse_day_1/FA/fa.v
module fa (
	input a,
	input b,
	input cin,
	output sum,
	output cout
);

wire ha_sum;
wire ha_carry;
wire temp;

ha i1 (.a(a),.b(b),.sum(ha_sum),.carry(ha_carry));

assign sum = ha_sum ^ cin;
assign temp = ha_sum & cin;
assign cout = temp | ha_carry;

endmodule

VeriVerse_day_1/Para_adder/para_adder_4.v
module para_adder_4 (
	input [3:0] a,
	input [3:0] b,
	input cin,
	output [3:0] sum,
	output [3:0] cout
);

fa i0 (.a(a[0]), .b(b[0]), .cin(cin), .sum(sum[0]), .cout(cout[0]));
fa i1 (.a(a[1]), .b(b[1]), .cin(cout[0]), .sum(sum[1]), .cout(cout[1]));
fa i2 (.a(a[2]), .b(b[2]), .cin(cout[1]), .sum(sum[2]), .cout(cout[2]));
fa i3 (.a(a[3]), .b(b[3]), .cin(cout[2]), .sum(sum[3]), .cout(cout[3]));

endmodule

VeriVerse_day_1/Para_adder/tb_para_adder_4.v
`timescale 1ns/1ps // setting time unit as 1ns and time precision as 1ps

module tb_para_adder_4 (); //instantiating verilog testbench

reg [3:0] a, b;  // outputs to be sent to design environment; stored in testbench
reg cin;  
wire [3:0] sum, cout;   // input received from design environment;

para_adder_4 dut (.a(a), .cout(cout), .b(b), .sum(sum), .cin(cin));
initial 
	begin
		$monitor("time = %d, a = %d, b = %d, cin = %d, sum = %d, cout = %d ", $time, a, b, cin, sum, cout);
	end
	
initial
	begin
		a = 0; b = 0; cin = 0; // at time interval 0 ns
		#10 //assign after 10ns delay
		a = 1; b = 1; // at time interval 10 ns
		#10
		a = 2; b = 2;// at time interval 20 ns
		#10 
		a = 4 ; b = 4;// at time interval 30 ns
		#10
		a = 5 ; b = 5;
		#10
		a = 6 ; b = 6;
		#10
		a = 7 ; b = 7;
		#10
		a = 8 ; b = 8;
		#10
		a = 9 ; b = 9;
		#10
		$finish;      // at time interval 40 ns
	end

initial
	begin
		$dumpfile("para_adder_4.vcd");
		$dumpvars;
	end
endmodule

VeriVerse_day_1/Para_adder/para_adder_4.vcd
$date
	Sun Dec 10 17:35:12 2023
$end
$version
	Icarus Verilog
$end
$timescale
	1ps
$end
$scope module tb_para_adder_4 $end
$var wire 4 ! sum [3:0] $end
$var wire 4 " cout [3:0] $end
$var reg 4 # a [3:0] $end
$var reg 4 $ b [3:0] $end
$var reg 1 % cin $end
$scope module dut $end
$var wire 4 & a [3:0] $end
$var wire 4 ' b [3:0] $end
$var wire 1 % cin $end
$var wire 4 ( sum [3:0] $end
$var wire 4 ) cout [3:0] $end
$scope module i0 $end
$var wire 1 * a $end
$var wire 1 + b $end
$var wire 1 % cin $end
$var wire 1 , cout $end
$var wire 1 - sum $end
$var wire 1 . temp $end
$var wire 1 / ha_sum $end
$var wire 1 0 ha_carry $end
$scope module i1 $end
$var wire 1 * a $end
$var wire 1 + b $end
$var wire 1 0 carry $end
$var wire 1 / sum $end
$upscope $end
$upscope $end
$scope module i1 $end
$var wire 1 1 a $end
$var wire 1 2 b $end
$var wire 1 3 cin $end
$var wire 1 4 cout $end
$var wire 1 5 sum $end
$var wire 1 6 temp $end
$var wire 1 7 ha_sum $end
$var wire 1 8 ha_carry $end
$scope module i1 $end
$var wire 1 1 a $end
$var wire 1 2 b $end
$var wire 1 8 carry $end
$var wire 1 7 sum $end
$upscope $end
$upscope $end
$scope module i2 $end
$var wire 1 9 a $end
$var wire 1 : b $end
$var wire 1 ; cin $end
$var wire 1 < cout $end
$var wire 1 = sum $end
$var wire 1 > temp $end
$var wire 1 ? ha_sum $end
$var wire 1 @ ha_carry $end
$scope module i1 $end
$var wire 1 9 a $end
$var wire 1 : b $end
$var wire 1 @ carry $end
$var wire 1 ? sum $end
$upscope $end
$upscope $end
$scope module i3 $end
$var wire 1 A a $end
$var wire 1 B b $end
$var wire 1 C cin $end
$var wire 1 D cout $end
$var wire 1 E sum $end
$var wire 1 F temp $end
$var wire 1 G ha_sum $end
$var wire 1 H ha_carry $end
$scope module i1 $end
$var wire 1 A a $end
$var wire 1 B b $end
$var wire 1 H carry $end
$var wire 1 G sum $end
$upscope $end
$upscope $end
$upscope $end
$upscope $end
$enddefinitions $end
#0
$dumpvars
0H
0G
0F
0E
0D
0C
0B
0A
0@
0?
0>
0=
0<
0;
0:
09
08
07
06
05
04
03
02
01
00
0/
0.
0-
0,
0+
0*
b0 )
b0 (
b0 '
b0 &
0%
b0 $
b0 #
b0 "
b0 !
$end
#10000
b10 !
b10 (
15
13
b1 "
b1 )
1,
10
1+
1*
b1 $
b1 '
b1 #
b1 &
#20000
05
b100 !
b100 (
1=
03
1;
0,
b10 "
b10 )
14
00
18
0+
12
0*
11
b10 $
b10 '
b10 #
b10 &
#30000
0=
b1000 !
b1000 (
1E
0;
1C
04
b100 "
b100 )
1<
08
1@
02
1:
01
19
b100 $
b100 '
b100 #
b100 &
#40000
b1010 !
b1010 (
15
13
b101 "
b101 )
1,
10
1+
1*
b101 $
b101 '
b101 #
b101 &
#50000
05
b1100 !
b1100 (
1=
03
1;
0,
b110 "
b110 )
14
00
18
0+
12
0*
11
b110 $
b110 '
b110 #
b110 &
#60000
b1110 !
b1110 (
15
13
b111 "
b111 )
1,
10
1+
1*
b111 $
b111 '
b111 #
b111 &
#70000
05
0=
b0 !
b0 (
0E
03
0;
0C
0,
04
0<
b1000 "
b1000 )
1D
00
08
0@
1H
0+
02
0:
1B
0*
01
09
1A
b1000 $
b1000 '
b1000 #
b1000 &
#80000
b10 !
b10 (
15
13
b1001 "
b1001 )
1,
10
1+
1*
b1001 $
b1001 '
b1001 #
b1001 &
